{
  "type": "Program",
  "body": [
    {
      "type": "ImportDeclaration",
      "specifiers": [
        {
          "type": "ImportDefaultSpecifier",
          "local": {
            "type": "Identifier",
            "name": "Subscriber",
            "range": [
              7,
              17
            ],
            "loc": {
              "start": {
                "line": 1,
                "column": 7
              },
              "end": {
                "line": 1,
                "column": 17
              }
            }
          },
          "range": [
            7,
            17
          ],
          "loc": {
            "start": {
              "line": 1,
              "column": 7
            },
            "end": {
              "line": 1,
              "column": 17
            }
          }
        }
      ],
      "source": {
        "type": "Literal",
        "value": "../Subscriber",
        "raw": "'../Subscriber'",
        "range": [
          23,
          38
        ],
        "loc": {
          "start": {
            "line": 1,
            "column": 23
          },
          "end": {
            "line": 1,
            "column": 38
          }
        }
      },
      "range": [
        0,
        39
      ],
      "loc": {
        "start": {
          "line": 1,
          "column": 0
        },
        "end": {
          "line": 1,
          "column": 39
        }
      }
    },
    {
      "type": "ImportDeclaration",
      "specifiers": [
        {
          "type": "ImportDefaultSpecifier",
          "local": {
            "type": "Identifier",
            "name": "immediate",
            "range": [
              47,
              56
            ],
            "loc": {
              "start": {
                "line": 2,
                "column": 7
              },
              "end": {
                "line": 2,
                "column": 16
              }
            }
          },
          "range": [
            47,
            56
          ],
          "loc": {
            "start": {
              "line": 2,
              "column": 7
            },
            "end": {
              "line": 2,
              "column": 16
            }
          }
        }
      ],
      "source": {
        "type": "Literal",
        "value": "../schedulers/immediate",
        "raw": "'../schedulers/immediate'",
        "range": [
          62,
          87
        ],
        "loc": {
          "start": {
            "line": 2,
            "column": 22
          },
          "end": {
            "line": 2,
            "column": 47
          }
        }
      },
      "range": [
        40,
        88
      ],
      "loc": {
        "start": {
          "line": 2,
          "column": 0
        },
        "end": {
          "line": 2,
          "column": 48
        }
      }
    },
    {
      "type": "ImportDeclaration",
      "specifiers": [
        {
          "type": "ImportDefaultSpecifier",
          "local": {
            "type": "Identifier",
            "name": "isDate",
            "range": [
              96,
              102
            ],
            "loc": {
              "start": {
                "line": 3,
                "column": 7
              },
              "end": {
                "line": 3,
                "column": 13
              }
            }
          },
          "range": [
            96,
            102
          ],
          "loc": {
            "start": {
              "line": 3,
              "column": 7
            },
            "end": {
              "line": 3,
              "column": 13
            }
          }
        }
      ],
      "source": {
        "type": "Literal",
        "value": "../util/isDate",
        "raw": "'../util/isDate'",
        "range": [
          108,
          124
        ],
        "loc": {
          "start": {
            "line": 3,
            "column": 19
          },
          "end": {
            "line": 3,
            "column": 35
          }
        }
      },
      "range": [
        89,
        125
      ],
      "loc": {
        "start": {
          "line": 3,
          "column": 0
        },
        "end": {
          "line": 3,
          "column": 36
        }
      }
    },
    {
      "type": "ExportDefaultDeclaration",
      "declaration": {
        "type": "FunctionDeclaration",
        "id": {
          "type": "Identifier",
          "name": "timeoutWith",
          "range": [
            150,
            161
          ],
          "loc": {
            "start": {
              "line": 4,
              "column": 24
            },
            "end": {
              "line": 4,
              "column": 35
            }
          }
        },
        "params": [
          {
            "type": "Identifier",
            "name": "due",
            "range": [
              162,
              165
            ],
            "loc": {
              "start": {
                "line": 4,
                "column": 36
              },
              "end": {
                "line": 4,
                "column": 39
              }
            }
          },
          {
            "type": "Identifier",
            "name": "withObservable",
            "range": [
              167,
              181
            ],
            "loc": {
              "start": {
                "line": 4,
                "column": 41
              },
              "end": {
                "line": 4,
                "column": 55
              }
            }
          },
          {
            "type": "AssignmentPattern",
            "left": {
              "type": "Identifier",
              "name": "scheduler",
              "range": [
                183,
                192
              ],
              "loc": {
                "start": {
                  "line": 4,
                  "column": 57
                },
                "end": {
                  "line": 4,
                  "column": 66
                }
              }
            },
            "right": {
              "type": "Identifier",
              "name": "immediate",
              "range": [
                195,
                204
              ],
              "loc": {
                "start": {
                  "line": 4,
                  "column": 69
                },
                "end": {
                  "line": 4,
                  "column": 78
                }
              }
            },
            "range": [
              183,
              204
            ],
            "loc": {
              "start": {
                "line": 4,
                "column": 57
              },
              "end": {
                "line": 4,
                "column": 78
              }
            }
          }
        ],
        "body": {
          "type": "BlockStatement",
          "body": [
            {
              "type": "VariableDeclaration",
              "declarations": [
                {
                  "type": "VariableDeclarator",
                  "id": {
                    "type": "Identifier",
                    "name": "waitFor",
                    "range": [
                      216,
                      223
                    ],
                    "loc": {
                      "start": {
                        "line": 5,
                        "column": 8
                      },
                      "end": {
                        "line": 5,
                        "column": 15
                      }
                    }
                  },
                  "init": {
                    "type": "ConditionalExpression",
                    "test": {
                      "type": "CallExpression",
                      "callee": {
                        "type": "Identifier",
                        "name": "isDate",
                        "range": [
                          226,
                          232
                        ],
                        "loc": {
                          "start": {
                            "line": 5,
                            "column": 18
                          },
                          "end": {
                            "line": 5,
                            "column": 24
                          }
                        }
                      },
                      "arguments": [
                        {
                          "type": "Identifier",
                          "name": "due",
                          "range": [
                            233,
                            236
                          ],
                          "loc": {
                            "start": {
                              "line": 5,
                              "column": 25
                            },
                            "end": {
                              "line": 5,
                              "column": 28
                            }
                          }
                        }
                      ],
                      "range": [
                        226,
                        237
                      ],
                      "loc": {
                        "start": {
                          "line": 5,
                          "column": 18
                        },
                        "end": {
                          "line": 5,
                          "column": 29
                        }
                      }
                    },
                    "consequent": {
                      "type": "BinaryExpression",
                      "operator": "-",
                      "left": {
                        "type": "UnaryExpression",
                        "operator": "+",
                        "argument": {
                          "type": "Identifier",
                          "name": "due",
                          "range": [
                            242,
                            245
                          ],
                          "loc": {
                            "start": {
                              "line": 5,
                              "column": 34
                            },
                            "end": {
                              "line": 5,
                              "column": 37
                            }
                          }
                        },
                        "prefix": true,
                        "range": [
                          241,
                          245
                        ],
                        "loc": {
                          "start": {
                            "line": 5,
                            "column": 33
                          },
                          "end": {
                            "line": 5,
                            "column": 37
                          }
                        }
                      },
                      "right": {
                        "type": "CallExpression",
                        "callee": {
                          "type": "MemberExpression",
                          "computed": false,
                          "object": {
                            "type": "Identifier",
                            "name": "Date",
                            "range": [
                              248,
                              252
                            ],
                            "loc": {
                              "start": {
                                "line": 5,
                                "column": 40
                              },
                              "end": {
                                "line": 5,
                                "column": 44
                              }
                            }
                          },
                          "property": {
                            "type": "Identifier",
                            "name": "now",
                            "range": [
                              253,
                              256
                            ],
                            "loc": {
                              "start": {
                                "line": 5,
                                "column": 45
                              },
                              "end": {
                                "line": 5,
                                "column": 48
                              }
                            }
                          },
                          "range": [
                            248,
                            256
                          ],
                          "loc": {
                            "start": {
                              "line": 5,
                              "column": 40
                            },
                            "end": {
                              "line": 5,
                              "column": 48
                            }
                          }
                        },
                        "arguments": [],
                        "range": [
                          248,
                          258
                        ],
                        "loc": {
                          "start": {
                            "line": 5,
                            "column": 40
                          },
                          "end": {
                            "line": 5,
                            "column": 50
                          }
                        }
                      },
                      "range": [
                        241,
                        258
                      ],
                      "loc": {
                        "start": {
                          "line": 5,
                          "column": 33
                        },
                        "end": {
                          "line": 5,
                          "column": 50
                        }
                      }
                    },
                    "alternate": {
                      "type": "Identifier",
                      "name": "due",
                      "range": [
                        262,
                        265
                      ],
                      "loc": {
                        "start": {
                          "line": 5,
                          "column": 54
                        },
                        "end": {
                          "line": 5,
                          "column": 57
                        }
                      }
                    },
                    "range": [
                      226,
                      265
                    ],
                    "loc": {
                      "start": {
                        "line": 5,
                        "column": 18
                      },
                      "end": {
                        "line": 5,
                        "column": 57
                      }
                    }
                  },
                  "range": [
                    216,
                    265
                  ],
                  "loc": {
                    "start": {
                      "line": 5,
                      "column": 8
                    },
                    "end": {
                      "line": 5,
                      "column": 57
                    }
                  }
                }
              ],
              "kind": "let",
              "range": [
                212,
                266
              ],
              "loc": {
                "start": {
                  "line": 5,
                  "column": 4
                },
                "end": {
                  "line": 5,
                  "column": 58
                }
              }
            },
            {
              "type": "ReturnStatement",
              "argument": {
                "type": "CallExpression",
                "callee": {
                  "type": "MemberExpression",
                  "computed": false,
                  "object": {
                    "type": "ThisExpression",
                    "range": [
                      278,
                      282
                    ],
                    "loc": {
                      "start": {
                        "line": 6,
                        "column": 11
                      },
                      "end": {
                        "line": 6,
                        "column": 15
                      }
                    }
                  },
                  "property": {
                    "type": "Identifier",
                    "name": "lift",
                    "range": [
                      283,
                      287
                    ],
                    "loc": {
                      "start": {
                        "line": 6,
                        "column": 16
                      },
                      "end": {
                        "line": 6,
                        "column": 20
                      }
                    }
                  },
                  "range": [
                    278,
                    287
                  ],
                  "loc": {
                    "start": {
                      "line": 6,
                      "column": 11
                    },
                    "end": {
                      "line": 6,
                      "column": 20
                    }
                  }
                },
                "arguments": [
                  {
                    "type": "NewExpression",
                    "callee": {
                      "type": "Identifier",
                      "name": "TimeoutWithOperator",
                      "range": [
                        292,
                        311
                      ],
                      "loc": {
                        "start": {
                          "line": 6,
                          "column": 25
                        },
                        "end": {
                          "line": 6,
                          "column": 44
                        }
                      }
                    },
                    "arguments": [
                      {
                        "type": "Identifier",
                        "name": "waitFor",
                        "range": [
                          312,
                          319
                        ],
                        "loc": {
                          "start": {
                            "line": 6,
                            "column": 45
                          },
                          "end": {
                            "line": 6,
                            "column": 52
                          }
                        }
                      },
                      {
                        "type": "Identifier",
                        "name": "withObservable",
                        "range": [
                          321,
                          335
                        ],
                        "loc": {
                          "start": {
                            "line": 6,
                            "column": 54
                          },
                          "end": {
                            "line": 6,
                            "column": 68
                          }
                        }
                      },
                      {
                        "type": "Identifier",
                        "name": "scheduler",
                        "range": [
                          337,
                          346
                        ],
                        "loc": {
                          "start": {
                            "line": 6,
                            "column": 70
                          },
                          "end": {
                            "line": 6,
                            "column": 79
                          }
                        }
                      }
                    ],
                    "range": [
                      288,
                      347
                    ],
                    "loc": {
                      "start": {
                        "line": 6,
                        "column": 21
                      },
                      "end": {
                        "line": 6,
                        "column": 80
                      }
                    }
                  }
                ],
                "range": [
                  278,
                  348
                ],
                "loc": {
                  "start": {
                    "line": 6,
                    "column": 11
                  },
                  "end": {
                    "line": 6,
                    "column": 81
                  }
                }
              },
              "range": [
                271,
                349
              ],
              "loc": {
                "start": {
                  "line": 6,
                  "column": 4
                },
                "end": {
                  "line": 6,
                  "column": 82
                }
              }
            }
          ],
          "range": [
            206,
            351
          ],
          "loc": {
            "start": {
              "line": 4,
              "column": 80
            },
            "end": {
              "line": 7,
              "column": 1
            }
          }
        },
        "generator": false,
        "expression": false,
        "range": [
          141,
          351
        ],
        "loc": {
          "start": {
            "line": 4,
            "column": 15
          },
          "end": {
            "line": 7,
            "column": 1
          }
        },
        "leadingComments": [],
        "trailingComments": []
      },
      "range": [
        126,
        351
      ],
      "loc": {
        "start": {
          "line": 4,
          "column": 0
        },
        "end": {
          "line": 7,
          "column": 1
        }
      }
    },
    {
      "type": "ClassDeclaration",
      "id": {
        "type": "Identifier",
        "name": "TimeoutWithOperator",
        "range": [
          358,
          377
        ],
        "loc": {
          "start": {
            "line": 8,
            "column": 6
          },
          "end": {
            "line": 8,
            "column": 25
          }
        }
      },
      "superClass": null,
      "body": {
        "type": "ClassBody",
        "body": [
          {
            "type": "MethodDefinition",
            "key": {
              "type": "Identifier",
              "name": "constructor",
              "range": [
                384,
                395
              ],
              "loc": {
                "start": {
                  "line": 9,
                  "column": 4
                },
                "end": {
                  "line": 9,
                  "column": 15
                }
              }
            },
            "value": {
              "type": "FunctionExpression",
              "id": null,
              "params": [
                {
                  "type": "Identifier",
                  "name": "waitFor",
                  "range": [
                    396,
                    403
                  ],
                  "loc": {
                    "start": {
                      "line": 9,
                      "column": 16
                    },
                    "end": {
                      "line": 9,
                      "column": 23
                    }
                  }
                },
                {
                  "type": "Identifier",
                  "name": "withObservable",
                  "range": [
                    405,
                    419
                  ],
                  "loc": {
                    "start": {
                      "line": 9,
                      "column": 25
                    },
                    "end": {
                      "line": 9,
                      "column": 39
                    }
                  }
                },
                {
                  "type": "Identifier",
                  "name": "scheduler",
                  "range": [
                    421,
                    430
                  ],
                  "loc": {
                    "start": {
                      "line": 9,
                      "column": 41
                    },
                    "end": {
                      "line": 9,
                      "column": 50
                    }
                  }
                }
              ],
              "body": {
                "type": "BlockStatement",
                "body": [
                  {
                    "type": "ExpressionStatement",
                    "expression": {
                      "type": "AssignmentExpression",
                      "operator": "=",
                      "left": {
                        "type": "MemberExpression",
                        "computed": false,
                        "object": {
                          "type": "ThisExpression",
                          "range": [
                            442,
                            446
                          ],
                          "loc": {
                            "start": {
                              "line": 10,
                              "column": 8
                            },
                            "end": {
                              "line": 10,
                              "column": 12
                            }
                          }
                        },
                        "property": {
                          "type": "Identifier",
                          "name": "waitFor",
                          "range": [
                            447,
                            454
                          ],
                          "loc": {
                            "start": {
                              "line": 10,
                              "column": 13
                            },
                            "end": {
                              "line": 10,
                              "column": 20
                            }
                          }
                        },
                        "range": [
                          442,
                          454
                        ],
                        "loc": {
                          "start": {
                            "line": 10,
                            "column": 8
                          },
                          "end": {
                            "line": 10,
                            "column": 20
                          }
                        }
                      },
                      "right": {
                        "type": "Identifier",
                        "name": "waitFor",
                        "range": [
                          457,
                          464
                        ],
                        "loc": {
                          "start": {
                            "line": 10,
                            "column": 23
                          },
                          "end": {
                            "line": 10,
                            "column": 30
                          }
                        }
                      },
                      "range": [
                        442,
                        464
                      ],
                      "loc": {
                        "start": {
                          "line": 10,
                          "column": 8
                        },
                        "end": {
                          "line": 10,
                          "column": 30
                        }
                      }
                    },
                    "range": [
                      442,
                      465
                    ],
                    "loc": {
                      "start": {
                        "line": 10,
                        "column": 8
                      },
                      "end": {
                        "line": 10,
                        "column": 31
                      }
                    }
                  },
                  {
                    "type": "ExpressionStatement",
                    "expression": {
                      "type": "AssignmentExpression",
                      "operator": "=",
                      "left": {
                        "type": "MemberExpression",
                        "computed": false,
                        "object": {
                          "type": "ThisExpression",
                          "range": [
                            474,
                            478
                          ],
                          "loc": {
                            "start": {
                              "line": 11,
                              "column": 8
                            },
                            "end": {
                              "line": 11,
                              "column": 12
                            }
                          }
                        },
                        "property": {
                          "type": "Identifier",
                          "name": "withObservable",
                          "range": [
                            479,
                            493
                          ],
                          "loc": {
                            "start": {
                              "line": 11,
                              "column": 13
                            },
                            "end": {
                              "line": 11,
                              "column": 27
                            }
                          }
                        },
                        "range": [
                          474,
                          493
                        ],
                        "loc": {
                          "start": {
                            "line": 11,
                            "column": 8
                          },
                          "end": {
                            "line": 11,
                            "column": 27
                          }
                        }
                      },
                      "right": {
                        "type": "Identifier",
                        "name": "withObservable",
                        "range": [
                          496,
                          510
                        ],
                        "loc": {
                          "start": {
                            "line": 11,
                            "column": 30
                          },
                          "end": {
                            "line": 11,
                            "column": 44
                          }
                        }
                      },
                      "range": [
                        474,
                        510
                      ],
                      "loc": {
                        "start": {
                          "line": 11,
                          "column": 8
                        },
                        "end": {
                          "line": 11,
                          "column": 44
                        }
                      }
                    },
                    "range": [
                      474,
                      511
                    ],
                    "loc": {
                      "start": {
                        "line": 11,
                        "column": 8
                      },
                      "end": {
                        "line": 11,
                        "column": 45
                      }
                    }
                  },
                  {
                    "type": "ExpressionStatement",
                    "expression": {
                      "type": "AssignmentExpression",
                      "operator": "=",
                      "left": {
                        "type": "MemberExpression",
                        "computed": false,
                        "object": {
                          "type": "ThisExpression",
                          "range": [
                            520,
                            524
                          ],
                          "loc": {
                            "start": {
                              "line": 12,
                              "column": 8
                            },
                            "end": {
                              "line": 12,
                              "column": 12
                            }
                          }
                        },
                        "property": {
                          "type": "Identifier",
                          "name": "scheduler",
                          "range": [
                            525,
                            534
                          ],
                          "loc": {
                            "start": {
                              "line": 12,
                              "column": 13
                            },
                            "end": {
                              "line": 12,
                              "column": 22
                            }
                          }
                        },
                        "range": [
                          520,
                          534
                        ],
                        "loc": {
                          "start": {
                            "line": 12,
                            "column": 8
                          },
                          "end": {
                            "line": 12,
                            "column": 22
                          }
                        }
                      },
                      "right": {
                        "type": "Identifier",
                        "name": "scheduler",
                        "range": [
                          537,
                          546
                        ],
                        "loc": {
                          "start": {
                            "line": 12,
                            "column": 25
                          },
                          "end": {
                            "line": 12,
                            "column": 34
                          }
                        }
                      },
                      "range": [
                        520,
                        546
                      ],
                      "loc": {
                        "start": {
                          "line": 12,
                          "column": 8
                        },
                        "end": {
                          "line": 12,
                          "column": 34
                        }
                      }
                    },
                    "range": [
                      520,
                      547
                    ],
                    "loc": {
                      "start": {
                        "line": 12,
                        "column": 8
                      },
                      "end": {
                        "line": 12,
                        "column": 35
                      }
                    }
                  }
                ],
                "range": [
                  432,
                  553
                ],
                "loc": {
                  "start": {
                    "line": 9,
                    "column": 52
                  },
                  "end": {
                    "line": 13,
                    "column": 5
                  }
                }
              },
              "generator": false,
              "expression": false,
              "range": [
                395,
                553
              ],
              "loc": {
                "start": {
                  "line": 9,
                  "column": 15
                },
                "end": {
                  "line": 13,
                  "column": 5
                }
              }
            },
            "kind": "constructor",
            "computed": false,
            "range": [
              384,
              553
            ],
            "loc": {
              "start": {
                "line": 9,
                "column": 4
              },
              "end": {
                "line": 13,
                "column": 5
              }
            },
            "static": false
          },
          {
            "type": "MethodDefinition",
            "key": {
              "type": "Identifier",
              "name": "call",
              "range": [
                558,
                562
              ],
              "loc": {
                "start": {
                  "line": 14,
                  "column": 4
                },
                "end": {
                  "line": 14,
                  "column": 8
                }
              }
            },
            "value": {
              "type": "FunctionExpression",
              "id": null,
              "params": [
                {
                  "type": "Identifier",
                  "name": "observer",
                  "range": [
                    563,
                    571
                  ],
                  "loc": {
                    "start": {
                      "line": 14,
                      "column": 9
                    },
                    "end": {
                      "line": 14,
                      "column": 17
                    }
                  }
                }
              ],
              "body": {
                "type": "BlockStatement",
                "body": [
                  {
                    "type": "ReturnStatement",
                    "argument": {
                      "type": "NewExpression",
                      "callee": {
                        "type": "Identifier",
                        "name": "TimeoutWithSubscriber",
                        "range": [
                          594,
                          615
                        ],
                        "loc": {
                          "start": {
                            "line": 15,
                            "column": 19
                          },
                          "end": {
                            "line": 15,
                            "column": 40
                          }
                        }
                      },
                      "arguments": [
                        {
                          "type": "Identifier",
                          "name": "observer",
                          "range": [
                            616,
                            624
                          ],
                          "loc": {
                            "start": {
                              "line": 15,
                              "column": 41
                            },
                            "end": {
                              "line": 15,
                              "column": 49
                            }
                          }
                        },
                        {
                          "type": "MemberExpression",
                          "computed": false,
                          "object": {
                            "type": "ThisExpression",
                            "range": [
                              626,
                              630
                            ],
                            "loc": {
                              "start": {
                                "line": 15,
                                "column": 51
                              },
                              "end": {
                                "line": 15,
                                "column": 55
                              }
                            }
                          },
                          "property": {
                            "type": "Identifier",
                            "name": "waitFor",
                            "range": [
                              631,
                              638
                            ],
                            "loc": {
                              "start": {
                                "line": 15,
                                "column": 56
                              },
                              "end": {
                                "line": 15,
                                "column": 63
                              }
                            }
                          },
                          "range": [
                            626,
                            638
                          ],
                          "loc": {
                            "start": {
                              "line": 15,
                              "column": 51
                            },
                            "end": {
                              "line": 15,
                              "column": 63
                            }
                          }
                        },
                        {
                          "type": "MemberExpression",
                          "computed": false,
                          "object": {
                            "type": "ThisExpression",
                            "range": [
                              640,
                              644
                            ],
                            "loc": {
                              "start": {
                                "line": 15,
                                "column": 65
                              },
                              "end": {
                                "line": 15,
                                "column": 69
                              }
                            }
                          },
                          "property": {
                            "type": "Identifier",
                            "name": "withObservable",
                            "range": [
                              645,
                              659
                            ],
                            "loc": {
                              "start": {
                                "line": 15,
                                "column": 70
                              },
                              "end": {
                                "line": 15,
                                "column": 84
                              }
                            }
                          },
                          "range": [
                            640,
                            659
                          ],
                          "loc": {
                            "start": {
                              "line": 15,
                              "column": 65
                            },
                            "end": {
                              "line": 15,
                              "column": 84
                            }
                          }
                        },
                        {
                          "type": "MemberExpression",
                          "computed": false,
                          "object": {
                            "type": "ThisExpression",
                            "range": [
                              661,
                              665
                            ],
                            "loc": {
                              "start": {
                                "line": 15,
                                "column": 86
                              },
                              "end": {
                                "line": 15,
                                "column": 90
                              }
                            }
                          },
                          "property": {
                            "type": "Identifier",
                            "name": "scheduler",
                            "range": [
                              666,
                              675
                            ],
                            "loc": {
                              "start": {
                                "line": 15,
                                "column": 91
                              },
                              "end": {
                                "line": 15,
                                "column": 100
                              }
                            }
                          },
                          "range": [
                            661,
                            675
                          ],
                          "loc": {
                            "start": {
                              "line": 15,
                              "column": 86
                            },
                            "end": {
                              "line": 15,
                              "column": 100
                            }
                          }
                        }
                      ],
                      "range": [
                        590,
                        676
                      ],
                      "loc": {
                        "start": {
                          "line": 15,
                          "column": 15
                        },
                        "end": {
                          "line": 15,
                          "column": 101
                        }
                      }
                    },
                    "range": [
                      583,
                      677
                    ],
                    "loc": {
                      "start": {
                        "line": 15,
                        "column": 8
                      },
                      "end": {
                        "line": 15,
                        "column": 102
                      }
                    }
                  }
                ],
                "range": [
                  573,
                  683
                ],
                "loc": {
                  "start": {
                    "line": 14,
                    "column": 19
                  },
                  "end": {
                    "line": 16,
                    "column": 5
                  }
                }
              },
              "generator": false,
              "expression": false,
              "range": [
                562,
                683
              ],
              "loc": {
                "start": {
                  "line": 14,
                  "column": 8
                },
                "end": {
                  "line": 16,
                  "column": 5
                }
              }
            },
            "kind": "method",
            "computed": false,
            "range": [
              558,
              683
            ],
            "loc": {
              "start": {
                "line": 14,
                "column": 4
              },
              "end": {
                "line": 16,
                "column": 5
              }
            },
            "static": false
          }
        ],
        "range": [
          378,
          685
        ],
        "loc": {
          "start": {
            "line": 8,
            "column": 26
          },
          "end": {
            "line": 17,
            "column": 1
          }
        }
      },
      "range": [
        352,
        685
      ],
      "loc": {
        "start": {
          "line": 8,
          "column": 0
        },
        "end": {
          "line": 17,
          "column": 1
        }
      }
    },
    {
      "type": "ClassDeclaration",
      "id": {
        "type": "Identifier",
        "name": "TimeoutWithSubscriber",
        "range": [
          692,
          713
        ],
        "loc": {
          "start": {
            "line": 18,
            "column": 6
          },
          "end": {
            "line": 18,
            "column": 27
          }
        }
      },
      "superClass": {
        "type": "Identifier",
        "name": "Subscriber",
        "range": [
          722,
          732
        ],
        "loc": {
          "start": {
            "line": 18,
            "column": 36
          },
          "end": {
            "line": 18,
            "column": 46
          }
        }
      },
      "body": {
        "type": "ClassBody",
        "body": [
          {
            "type": "MethodDefinition",
            "key": {
              "type": "Identifier",
              "name": "constructor",
              "range": [
                739,
                750
              ],
              "loc": {
                "start": {
                  "line": 19,
                  "column": 4
                },
                "end": {
                  "line": 19,
                  "column": 15
                }
              }
            },
            "value": {
              "type": "FunctionExpression",
              "id": null,
              "params": [
                {
                  "type": "Identifier",
                  "name": "destination",
                  "range": [
                    751,
                    762
                  ],
                  "loc": {
                    "start": {
                      "line": 19,
                      "column": 16
                    },
                    "end": {
                      "line": 19,
                      "column": 27
                    }
                  }
                },
                {
                  "type": "Identifier",
                  "name": "waitFor",
                  "range": [
                    764,
                    771
                  ],
                  "loc": {
                    "start": {
                      "line": 19,
                      "column": 29
                    },
                    "end": {
                      "line": 19,
                      "column": 36
                    }
                  }
                },
                {
                  "type": "Identifier",
                  "name": "withObservable",
                  "range": [
                    773,
                    787
                  ],
                  "loc": {
                    "start": {
                      "line": 19,
                      "column": 38
                    },
                    "end": {
                      "line": 19,
                      "column": 52
                    }
                  }
                },
                {
                  "type": "Identifier",
                  "name": "scheduler",
                  "range": [
                    789,
                    798
                  ],
                  "loc": {
                    "start": {
                      "line": 19,
                      "column": 54
                    },
                    "end": {
                      "line": 19,
                      "column": 63
                    }
                  }
                }
              ],
              "body": {
                "type": "BlockStatement",
                "body": [
                  {
                    "type": "ExpressionStatement",
                    "expression": {
                      "type": "CallExpression",
                      "callee": {
                        "type": "Super",
                        "range": [
                          810,
                          815
                        ],
                        "loc": {
                          "start": {
                            "line": 20,
                            "column": 8
                          },
                          "end": {
                            "line": 20,
                            "column": 13
                          }
                        }
                      },
                      "arguments": [
                        {
                          "type": "Identifier",
                          "name": "destination",
                          "range": [
                            816,
                            827
                          ],
                          "loc": {
                            "start": {
                              "line": 20,
                              "column": 14
                            },
                            "end": {
                              "line": 20,
                              "column": 25
                            }
                          }
                        }
                      ],
                      "range": [
                        810,
                        828
                      ],
                      "loc": {
                        "start": {
                          "line": 20,
                          "column": 8
                        },
                        "end": {
                          "line": 20,
                          "column": 26
                        }
                      }
                    },
                    "range": [
                      810,
                      829
                    ],
                    "loc": {
                      "start": {
                        "line": 20,
                        "column": 8
                      },
                      "end": {
                        "line": 20,
                        "column": 27
                      }
                    }
                  },
                  {
                    "type": "ExpressionStatement",
                    "expression": {
                      "type": "AssignmentExpression",
                      "operator": "=",
                      "left": {
                        "type": "MemberExpression",
                        "computed": false,
                        "object": {
                          "type": "ThisExpression",
                          "range": [
                            838,
                            842
                          ],
                          "loc": {
                            "start": {
                              "line": 21,
                              "column": 8
                            },
                            "end": {
                              "line": 21,
                              "column": 12
                            }
                          }
                        },
                        "property": {
                          "type": "Identifier",
                          "name": "waitFor",
                          "range": [
                            843,
                            850
                          ],
                          "loc": {
                            "start": {
                              "line": 21,
                              "column": 13
                            },
                            "end": {
                              "line": 21,
                              "column": 20
                            }
                          }
                        },
                        "range": [
                          838,
                          850
                        ],
                        "loc": {
                          "start": {
                            "line": 21,
                            "column": 8
                          },
                          "end": {
                            "line": 21,
                            "column": 20
                          }
                        }
                      },
                      "right": {
                        "type": "Identifier",
                        "name": "waitFor",
                        "range": [
                          853,
                          860
                        ],
                        "loc": {
                          "start": {
                            "line": 21,
                            "column": 23
                          },
                          "end": {
                            "line": 21,
                            "column": 30
                          }
                        }
                      },
                      "range": [
                        838,
                        860
                      ],
                      "loc": {
                        "start": {
                          "line": 21,
                          "column": 8
                        },
                        "end": {
                          "line": 21,
                          "column": 30
                        }
                      }
                    },
                    "range": [
                      838,
                      861
                    ],
                    "loc": {
                      "start": {
                        "line": 21,
                        "column": 8
                      },
                      "end": {
                        "line": 21,
                        "column": 31
                      }
                    }
                  },
                  {
                    "type": "ExpressionStatement",
                    "expression": {
                      "type": "AssignmentExpression",
                      "operator": "=",
                      "left": {
                        "type": "MemberExpression",
                        "computed": false,
                        "object": {
                          "type": "ThisExpression",
                          "range": [
                            870,
                            874
                          ],
                          "loc": {
                            "start": {
                              "line": 22,
                              "column": 8
                            },
                            "end": {
                              "line": 22,
                              "column": 12
                            }
                          }
                        },
                        "property": {
                          "type": "Identifier",
                          "name": "withObservable",
                          "range": [
                            875,
                            889
                          ],
                          "loc": {
                            "start": {
                              "line": 22,
                              "column": 13
                            },
                            "end": {
                              "line": 22,
                              "column": 27
                            }
                          }
                        },
                        "range": [
                          870,
                          889
                        ],
                        "loc": {
                          "start": {
                            "line": 22,
                            "column": 8
                          },
                          "end": {
                            "line": 22,
                            "column": 27
                          }
                        }
                      },
                      "right": {
                        "type": "Identifier",
                        "name": "withObservable",
                        "range": [
                          892,
                          906
                        ],
                        "loc": {
                          "start": {
                            "line": 22,
                            "column": 30
                          },
                          "end": {
                            "line": 22,
                            "column": 44
                          }
                        }
                      },
                      "range": [
                        870,
                        906
                      ],
                      "loc": {
                        "start": {
                          "line": 22,
                          "column": 8
                        },
                        "end": {
                          "line": 22,
                          "column": 44
                        }
                      }
                    },
                    "range": [
                      870,
                      907
                    ],
                    "loc": {
                      "start": {
                        "line": 22,
                        "column": 8
                      },
                      "end": {
                        "line": 22,
                        "column": 45
                      }
                    }
                  },
                  {
                    "type": "ExpressionStatement",
                    "expression": {
                      "type": "AssignmentExpression",
                      "operator": "=",
                      "left": {
                        "type": "MemberExpression",
                        "computed": false,
                        "object": {
                          "type": "ThisExpression",
                          "range": [
                            916,
                            920
                          ],
                          "loc": {
                            "start": {
                              "line": 23,
                              "column": 8
                            },
                            "end": {
                              "line": 23,
                              "column": 12
                            }
                          }
                        },
                        "property": {
                          "type": "Identifier",
                          "name": "scheduler",
                          "range": [
                            921,
                            930
                          ],
                          "loc": {
                            "start": {
                              "line": 23,
                              "column": 13
                            },
                            "end": {
                              "line": 23,
                              "column": 22
                            }
                          }
                        },
                        "range": [
                          916,
                          930
                        ],
                        "loc": {
                          "start": {
                            "line": 23,
                            "column": 8
                          },
                          "end": {
                            "line": 23,
                            "column": 22
                          }
                        }
                      },
                      "right": {
                        "type": "Identifier",
                        "name": "scheduler",
                        "range": [
                          933,
                          942
                        ],
                        "loc": {
                          "start": {
                            "line": 23,
                            "column": 25
                          },
                          "end": {
                            "line": 23,
                            "column": 34
                          }
                        }
                      },
                      "range": [
                        916,
                        942
                      ],
                      "loc": {
                        "start": {
                          "line": 23,
                          "column": 8
                        },
                        "end": {
                          "line": 23,
                          "column": 34
                        }
                      }
                    },
                    "range": [
                      916,
                      943
                    ],
                    "loc": {
                      "start": {
                        "line": 23,
                        "column": 8
                      },
                      "end": {
                        "line": 23,
                        "column": 35
                      }
                    }
                  },
                  {
                    "type": "VariableDeclaration",
                    "declarations": [
                      {
                        "type": "VariableDeclarator",
                        "id": {
                          "type": "Identifier",
                          "name": "delay",
                          "range": [
                            956,
                            961
                          ],
                          "loc": {
                            "start": {
                              "line": 24,
                              "column": 12
                            },
                            "end": {
                              "line": 24,
                              "column": 17
                            }
                          }
                        },
                        "init": {
                          "type": "Identifier",
                          "name": "waitFor",
                          "range": [
                            964,
                            971
                          ],
                          "loc": {
                            "start": {
                              "line": 24,
                              "column": 20
                            },
                            "end": {
                              "line": 24,
                              "column": 27
                            }
                          }
                        },
                        "range": [
                          956,
                          971
                        ],
                        "loc": {
                          "start": {
                            "line": 24,
                            "column": 12
                          },
                          "end": {
                            "line": 24,
                            "column": 27
                          }
                        }
                      }
                    ],
                    "kind": "let",
                    "range": [
                      952,
                      972
                    ],
                    "loc": {
                      "start": {
                        "line": 24,
                        "column": 8
                      },
                      "end": {
                        "line": 24,
                        "column": 28
                      }
                    }
                  },
                  {
                    "type": "ExpressionStatement",
                    "expression": {
                      "type": "CallExpression",
                      "callee": {
                        "type": "MemberExpression",
                        "computed": false,
                        "object": {
                          "type": "Identifier",
                          "name": "scheduler",
                          "range": [
                            981,
                            990
                          ],
                          "loc": {
                            "start": {
                              "line": 25,
                              "column": 8
                            },
                            "end": {
                              "line": 25,
                              "column": 17
                            }
                          }
                        },
                        "property": {
                          "type": "Identifier",
                          "name": "schedule",
                          "range": [
                            991,
                            999
                          ],
                          "loc": {
                            "start": {
                              "line": 25,
                              "column": 18
                            },
                            "end": {
                              "line": 25,
                              "column": 26
                            }
                          }
                        },
                        "range": [
                          981,
                          999
                        ],
                        "loc": {
                          "start": {
                            "line": 25,
                            "column": 8
                          },
                          "end": {
                            "line": 25,
                            "column": 26
                          }
                        }
                      },
                      "arguments": [
                        {
                          "type": "Identifier",
                          "name": "dispatchTimeout",
                          "range": [
                            1000,
                            1015
                          ],
                          "loc": {
                            "start": {
                              "line": 25,
                              "column": 27
                            },
                            "end": {
                              "line": 25,
                              "column": 42
                            }
                          }
                        },
                        {
                          "type": "Identifier",
                          "name": "delay",
                          "range": [
                            1017,
                            1022
                          ],
                          "loc": {
                            "start": {
                              "line": 25,
                              "column": 44
                            },
                            "end": {
                              "line": 25,
                              "column": 49
                            }
                          }
                        },
                        {
                          "type": "ObjectExpression",
                          "properties": [
                            {
                              "type": "Property",
                              "key": {
                                "type": "Identifier",
                                "name": "subscriber",
                                "range": [
                                  1026,
                                  1036
                                ],
                                "loc": {
                                  "start": {
                                    "line": 25,
                                    "column": 53
                                  },
                                  "end": {
                                    "line": 25,
                                    "column": 63
                                  }
                                }
                              },
                              "value": {
                                "type": "ThisExpression",
                                "range": [
                                  1038,
                                  1042
                                ],
                                "loc": {
                                  "start": {
                                    "line": 25,
                                    "column": 65
                                  },
                                  "end": {
                                    "line": 25,
                                    "column": 69
                                  }
                                }
                              },
                              "kind": "init",
                              "method": false,
                              "shorthand": false,
                              "computed": false,
                              "range": [
                                1026,
                                1042
                              ],
                              "loc": {
                                "start": {
                                  "line": 25,
                                  "column": 53
                                },
                                "end": {
                                  "line": 25,
                                  "column": 69
                                }
                              }
                            }
                          ],
                          "range": [
                            1024,
                            1044
                          ],
                          "loc": {
                            "start": {
                              "line": 25,
                              "column": 51
                            },
                            "end": {
                              "line": 25,
                              "column": 71
                            }
                          }
                        }
                      ],
                      "range": [
                        981,
                        1045
                      ],
                      "loc": {
                        "start": {
                          "line": 25,
                          "column": 8
                        },
                        "end": {
                          "line": 25,
                          "column": 72
                        }
                      }
                    },
                    "range": [
                      981,
                      1046
                    ],
                    "loc": {
                      "start": {
                        "line": 25,
                        "column": 8
                      },
                      "end": {
                        "line": 25,
                        "column": 73
                      }
                    }
                  }
                ],
                "range": [
                  800,
                  1052
                ],
                "loc": {
                  "start": {
                    "line": 19,
                    "column": 65
                  },
                  "end": {
                    "line": 26,
                    "column": 5
                  }
                }
              },
              "generator": false,
              "expression": false,
              "range": [
                750,
                1052
              ],
              "loc": {
                "start": {
                  "line": 19,
                  "column": 15
                },
                "end": {
                  "line": 26,
                  "column": 5
                }
              }
            },
            "kind": "constructor",
            "computed": false,
            "range": [
              739,
              1052
            ],
            "loc": {
              "start": {
                "line": 19,
                "column": 4
              },
              "end": {
                "line": 26,
                "column": 5
              }
            },
            "static": false
          },
          {
            "type": "MethodDefinition",
            "key": {
              "type": "Identifier",
              "name": "handleTimeout",
              "range": [
                1057,
                1070
              ],
              "loc": {
                "start": {
                  "line": 27,
                  "column": 4
                },
                "end": {
                  "line": 27,
                  "column": 17
                }
              }
            },
            "value": {
              "type": "FunctionExpression",
              "id": null,
              "params": [],
              "body": {
                "type": "BlockStatement",
                "body": [
                  {
                    "type": "VariableDeclaration",
                    "declarations": [
                      {
                        "type": "VariableDeclarator",
                        "id": {
                          "type": "Identifier",
                          "name": "withObservable",
                          "range": [
                            1089,
                            1103
                          ],
                          "loc": {
                            "start": {
                              "line": 28,
                              "column": 14
                            },
                            "end": {
                              "line": 28,
                              "column": 28
                            }
                          }
                        },
                        "init": {
                          "type": "MemberExpression",
                          "computed": false,
                          "object": {
                            "type": "ThisExpression",
                            "range": [
                              1106,
                              1110
                            ],
                            "loc": {
                              "start": {
                                "line": 28,
                                "column": 31
                              },
                              "end": {
                                "line": 28,
                                "column": 35
                              }
                            }
                          },
                          "property": {
                            "type": "Identifier",
                            "name": "withObservable",
                            "range": [
                              1111,
                              1125
                            ],
                            "loc": {
                              "start": {
                                "line": 28,
                                "column": 36
                              },
                              "end": {
                                "line": 28,
                                "column": 50
                              }
                            }
                          },
                          "range": [
                            1106,
                            1125
                          ],
                          "loc": {
                            "start": {
                              "line": 28,
                              "column": 31
                            },
                            "end": {
                              "line": 28,
                              "column": 50
                            }
                          }
                        },
                        "range": [
                          1089,
                          1125
                        ],
                        "loc": {
                          "start": {
                            "line": 28,
                            "column": 14
                          },
                          "end": {
                            "line": 28,
                            "column": 50
                          }
                        }
                      }
                    ],
                    "kind": "const",
                    "range": [
                      1083,
                      1126
                    ],
                    "loc": {
                      "start": {
                        "line": 28,
                        "column": 8
                      },
                      "end": {
                        "line": 28,
                        "column": 51
                      }
                    }
                  },
                  {
                    "type": "ExpressionStatement",
                    "expression": {
                      "type": "CallExpression",
                      "callee": {
                        "type": "MemberExpression",
                        "computed": false,
                        "object": {
                          "type": "ThisExpression",
                          "range": [
                            1135,
                            1139
                          ],
                          "loc": {
                            "start": {
                              "line": 29,
                              "column": 8
                            },
                            "end": {
                              "line": 29,
                              "column": 12
                            }
                          }
                        },
                        "property": {
                          "type": "Identifier",
                          "name": "add",
                          "range": [
                            1140,
                            1143
                          ],
                          "loc": {
                            "start": {
                              "line": 29,
                              "column": 13
                            },
                            "end": {
                              "line": 29,
                              "column": 16
                            }
                          }
                        },
                        "range": [
                          1135,
                          1143
                        ],
                        "loc": {
                          "start": {
                            "line": 29,
                            "column": 8
                          },
                          "end": {
                            "line": 29,
                            "column": 16
                          }
                        }
                      },
                      "arguments": [
                        {
                          "type": "CallExpression",
                          "callee": {
                            "type": "MemberExpression",
                            "computed": false,
                            "object": {
                              "type": "Identifier",
                              "name": "withObservable",
                              "range": [
                                1144,
                                1158
                              ],
                              "loc": {
                                "start": {
                                  "line": 29,
                                  "column": 17
                                },
                                "end": {
                                  "line": 29,
                                  "column": 31
                                }
                              }
                            },
                            "property": {
                              "type": "Identifier",
                              "name": "subscribe",
                              "range": [
                                1159,
                                1168
                              ],
                              "loc": {
                                "start": {
                                  "line": 29,
                                  "column": 32
                                },
                                "end": {
                                  "line": 29,
                                  "column": 41
                                }
                              }
                            },
                            "range": [
                              1144,
                              1168
                            ],
                            "loc": {
                              "start": {
                                "line": 29,
                                "column": 17
                              },
                              "end": {
                                "line": 29,
                                "column": 41
                              }
                            }
                          },
                          "arguments": [
                            {
                              "type": "ThisExpression",
                              "range": [
                                1169,
                                1173
                              ],
                              "loc": {
                                "start": {
                                  "line": 29,
                                  "column": 42
                                },
                                "end": {
                                  "line": 29,
                                  "column": 46
                                }
                              }
                            }
                          ],
                          "range": [
                            1144,
                            1174
                          ],
                          "loc": {
                            "start": {
                              "line": 29,
                              "column": 17
                            },
                            "end": {
                              "line": 29,
                              "column": 47
                            }
                          }
                        }
                      ],
                      "range": [
                        1135,
                        1175
                      ],
                      "loc": {
                        "start": {
                          "line": 29,
                          "column": 8
                        },
                        "end": {
                          "line": 29,
                          "column": 48
                        }
                      }
                    },
                    "range": [
                      1135,
                      1176
                    ],
                    "loc": {
                      "start": {
                        "line": 29,
                        "column": 8
                      },
                      "end": {
                        "line": 29,
                        "column": 49
                      }
                    }
                  }
                ],
                "range": [
                  1073,
                  1182
                ],
                "loc": {
                  "start": {
                    "line": 27,
                    "column": 20
                  },
                  "end": {
                    "line": 30,
                    "column": 5
                  }
                }
              },
              "generator": false,
              "expression": false,
              "range": [
                1070,
                1182
              ],
              "loc": {
                "start": {
                  "line": 27,
                  "column": 17
                },
                "end": {
                  "line": 30,
                  "column": 5
                }
              }
            },
            "kind": "method",
            "computed": false,
            "range": [
              1057,
              1182
            ],
            "loc": {
              "start": {
                "line": 27,
                "column": 4
              },
              "end": {
                "line": 30,
                "column": 5
              }
            },
            "static": false
          }
        ],
        "range": [
          733,
          1184
        ],
        "loc": {
          "start": {
            "line": 18,
            "column": 47
          },
          "end": {
            "line": 31,
            "column": 1
          }
        }
      },
      "range": [
        686,
        1184
      ],
      "loc": {
        "start": {
          "line": 18,
          "column": 0
        },
        "end": {
          "line": 31,
          "column": 1
        }
      }
    },
    {
      "type": "FunctionDeclaration",
      "id": {
        "type": "Identifier",
        "name": "dispatchTimeout",
        "range": [
          1194,
          1209
        ],
        "loc": {
          "start": {
            "line": 32,
            "column": 9
          },
          "end": {
            "line": 32,
            "column": 24
          }
        }
      },
      "params": [
        {
          "type": "Identifier",
          "name": "state",
          "range": [
            1210,
            1215
          ],
          "loc": {
            "start": {
              "line": 32,
              "column": 25
            },
            "end": {
              "line": 32,
              "column": 30
            }
          }
        }
      ],
      "body": {
        "type": "BlockStatement",
        "body": [
          {
            "type": "VariableDeclaration",
            "declarations": [
              {
                "type": "VariableDeclarator",
                "id": {
                  "type": "Identifier",
                  "name": "subscriber",
                  "range": [
                    1229,
                    1239
                  ],
                  "loc": {
                    "start": {
                      "line": 33,
                      "column": 10
                    },
                    "end": {
                      "line": 33,
                      "column": 20
                    }
                  }
                },
                "init": {
                  "type": "MemberExpression",
                  "computed": false,
                  "object": {
                    "type": "Identifier",
                    "name": "state",
                    "range": [
                      1242,
                      1247
                    ],
                    "loc": {
                      "start": {
                        "line": 33,
                        "column": 23
                      },
                      "end": {
                        "line": 33,
                        "column": 28
                      }
                    }
                  },
                  "property": {
                    "type": "Identifier",
                    "name": "subscriber",
                    "range": [
                      1248,
                      1258
                    ],
                    "loc": {
                      "start": {
                        "line": 33,
                        "column": 29
                      },
                      "end": {
                        "line": 33,
                        "column": 39
                      }
                    }
                  },
                  "range": [
                    1242,
                    1258
                  ],
                  "loc": {
                    "start": {
                      "line": 33,
                      "column": 23
                    },
                    "end": {
                      "line": 33,
                      "column": 39
                    }
                  }
                },
                "range": [
                  1229,
                  1258
                ],
                "loc": {
                  "start": {
                    "line": 33,
                    "column": 10
                  },
                  "end": {
                    "line": 33,
                    "column": 39
                  }
                }
              }
            ],
            "kind": "const",
            "range": [
              1223,
              1259
            ],
            "loc": {
              "start": {
                "line": 33,
                "column": 4
              },
              "end": {
                "line": 33,
                "column": 40
              }
            }
          },
          {
            "type": "ExpressionStatement",
            "expression": {
              "type": "CallExpression",
              "callee": {
                "type": "MemberExpression",
                "computed": false,
                "object": {
                  "type": "Identifier",
                  "name": "subscriber",
                  "range": [
                    1264,
                    1274
                  ],
                  "loc": {
                    "start": {
                      "line": 34,
                      "column": 4
                    },
                    "end": {
                      "line": 34,
                      "column": 14
                    }
                  }
                },
                "property": {
                  "type": "Identifier",
                  "name": "handleTimeout",
                  "range": [
                    1275,
                    1288
                  ],
                  "loc": {
                    "start": {
                      "line": 34,
                      "column": 15
                    },
                    "end": {
                      "line": 34,
                      "column": 28
                    }
                  }
                },
                "range": [
                  1264,
                  1288
                ],
                "loc": {
                  "start": {
                    "line": 34,
                    "column": 4
                  },
                  "end": {
                    "line": 34,
                    "column": 28
                  }
                }
              },
              "arguments": [],
              "range": [
                1264,
                1290
              ],
              "loc": {
                "start": {
                  "line": 34,
                  "column": 4
                },
                "end": {
                  "line": 34,
                  "column": 30
                }
              }
            },
            "range": [
              1264,
              1291
            ],
            "loc": {
              "start": {
                "line": 34,
                "column": 4
              },
              "end": {
                "line": 34,
                "column": 31
              }
            }
          }
        ],
        "range": [
          1217,
          1293
        ],
        "loc": {
          "start": {
            "line": 32,
            "column": 32
          },
          "end": {
            "line": 35,
            "column": 1
          }
        }
      },
      "generator": false,
      "expression": false,
      "range": [
        1185,
        1293
      ],
      "loc": {
        "start": {
          "line": 32,
          "column": 0
        },
        "end": {
          "line": 35,
          "column": 1
        }
      }
    }
  ],
  "sourceType": "module",
  "range": [
    0,
    1293
  ],
  "loc": {
    "start": {
      "line": 1,
      "column": 0
    },
    "end": {
      "line": 35,
      "column": 1
    }
  },
  "comments": []
}